integration_tests/__init__.py
integration_tests/batch_pipeline1.py
integration_tests/integration_test1.py
integration_tests/integration_test2.py
integration_tests/integration_test3.py
step_pipeline/__init__.py
step_pipeline/batch.py
step_pipeline/constants.py
step_pipeline/io.py
step_pipeline/main.py
step_pipeline/pipeline.py
step_pipeline/utils.py
step_pipeline/wdl.py
tests/__init__.py
tests/utils_tests.py
step_pipeline-0.2.7.dist-info/LICENSE
step_pipeline-0.2.7.dist-info/METADATA
step_pipeline-0.2.7.dist-info/WHEEL
step_pipeline-0.2.7.dist-info/top_level.txt
step_pipeline-0.2.7.dist-info/RECORD
