Metadata-Version: 2.1
Name: step-pipeline
Version: 0.2.7
Summary: Pipeline library that simplifies creation of pipelines that run on top of hail Batch and other compute enviornments
Home-page: https://github.com/broadinstitute/step_pipeline
License: MIT
Keywords: pipelines,workflows,hail,Batch,cromwell,Terra,dsub,SGE
Classifier: Development Status :: 4 - Beta
Classifier: Intended Audience :: Developers
Classifier: License :: OSI Approved :: MIT License
Classifier: Natural Language :: English
Classifier: Programming Language :: Python :: 3
Classifier: Programming Language :: Python :: 3.7
Classifier: Programming Language :: Python :: 3.8
Classifier: Programming Language :: Python :: 3.9
Classifier: Programming Language :: Python :: Implementation :: CPython
Classifier: Programming Language :: Python :: Implementation :: PyPy
Requires-Python: >=3.7
License-File: LICENSE
Requires-Dist: configargparse (>=1.4.1)
Requires-Dist: hail
Requires-Dist: google-cloud-storage
Requires-Dist: mock
Requires-Dist: tox
Requires-Dist: tox-venv
Requires-Dist: sphinxcontrib-napoleon
